commandman/__init__.py
commandman/app.py
commandman/commander.py
commandman/config.py
commandman/manager.py
commandman-0.5.2.dist-info/licenses/LICENSE
commandman-0.5.2.dist-info/METADATA
commandman-0.5.2.dist-info/WHEEL
commandman-0.5.2.dist-info/entry_points.txt
commandman-0.5.2.dist-info/top_level.txt
commandman-0.5.2.dist-info/RECORD
