Metadata-Version: 2.4
Name: commandman
Version: 0.5.2
Summary: Console utility for working with command packages. Storage, execution, autorun.
Home-page: https://github.com/smartlegionlab/commandman/
Author: A.A. Suvorov
Author-email: smartlegiondev@gmail.com
License: BSD 3-Clause License
Project-URL: Documentation, https://github.com/smartlegionlab/commandman/blob/master/README.md
Project-URL: Release notes, https://github.com/smartlegionlab/commandman/releases
Keywords: commandpack,commandoro,commandman,smartlegionlab,command execution
Classifier: Development Status :: 5 - Production/Stable
Classifier: Environment :: Console
Classifier: Intended Audience :: End Users/Desktop
Classifier: Intended Audience :: System Administrators
Classifier: License :: OSI Approved :: BSD License
Classifier: Natural Language :: English
Classifier: Operating System :: OS Independent
Classifier: Operating System :: Microsoft :: Windows
Classifier: Operating System :: POSIX :: Linux
Classifier: Programming Language :: Python :: 3 :: Only
Classifier: Topic :: Software Development :: Libraries :: Python Modules
Classifier: Topic :: Utilities
Requires-Python: >=3.6
License-File: LICENSE
Requires-Dist: click==8.0.1
Requires-Dist: smartcliapp==0.4.0
Requires-Dist: commandex==0.2.2
Dynamic: license-file
